signalslite/__init__.py
signalslite/constants.py
signalslite/data_downloader.py
signalslite/data_utils.py
signalslite/merge_targets.py
signalslite/primary_features.py
signalslite/run_pipeline.py
signalslite/scale_data.py
signalslite/secondary_features.py
signalslite/technical_features.py
signalslite-0.1a4.dist-info/LICENSE
signalslite-0.1a4.dist-info/METADATA
signalslite-0.1a4.dist-info/WHEEL
signalslite-0.1a4.dist-info/top_level.txt
signalslite-0.1a4.dist-info/RECORD
