Metadata-Version: 2.1
Name: signalslite
Version: 0.1a4
Summary: A small package for Numerai Signals locally
Home-page: https://github.com/parmarsuraj99/signalslite
Author: Suraj Parmar
Author-email: parmarsuraj99@gmail.com
License: UNKNOWN
Platform: UNKNOWN
Classifier: Programming Language :: Python :: 3
Classifier: License :: OSI Approved :: MIT License
Classifier: Operating System :: OS Independent
Requires-Python: >=3.8
